[
  {
    "file": "ACT_CHEN_DIRECT_RETEST.png",
    "width": 1672,
    "height": 941,
    "mode": "RGBA",
    "category": "ACT"
  },
  {
    "file": "ACT_CHEN_LISTEN_AND_CHECK.png",
    "width": 1672,
    "height": 941,
    "mode": "RGBA",
    "category": "ACT"
  },
  {
    "file": "ACT_CHEN_RULE_REMINDER.png",
    "width": 1672,
    "height": 941,
    "mode": "RGBA",
    "category": "ACT"
  },
  {
    "file": "ACT_LI_DIRECT_SUPPORT.png",
    "width": 1672,
    "height": 941,
    "mode": "RGBA",
    "category": "ACT"
  },
  {
    "file": "ACT_LI_PRIVATE_GUIDANCE.png",
    "width": 1672,
    "height": 941,
    "mode": "RGBA",
    "category": "ACT"
  },
  {
    "file": "ACT_LI_PUBLIC_COMMAND.png",
    "width": 1672,
    "height": 941,
    "mode": "RGBA",
    "category": "ACT"
  },
  {
    "file": "ACT_WANG_ASSIST_RESPECTFULLY.png",
    "width": 1672,
    "height": 941,
    "mode": "RGBA",
    "category": "ACT"
  },
  {
    "file": "ACT_WANG_DIRECT_FEED.png",
    "width": 1672,
    "height": 941,
    "mode": "RGBA",
    "category": "ACT"
  },
  {
    "file": "ACT_WANG_LEAVE.png",
    "width": 1672,
    "height": 941,
    "mode": "RGBA",
    "category": "ACT"
  },
  {
    "file": "ANM_CHEN_FOOD_HESITATE_01.png",
    "width": 1672,
    "height": 941,
    "mode": "RGBA",
    "category": "ANM"
  },
  {
    "file": "ANM_CHEN_FOOD_HESITATE_02.png",
    "width": 1672,
    "height": 941,
    "mode": "RGBA",
    "category": "ANM"
  },
  {
    "file": "ANM_CHEN_GLUCOSE_IDLE_01.png",
    "width": 1672,
    "height": 941,
    "mode": "RGBA",
    "category": "ANM"
  },
  {
    "file": "ANM_CHEN_GLUCOSE_IDLE_02.png",
    "width": 1672,
    "height": 941,
    "mode": "RGBA",
    "category": "ANM"
  },
  {
    "file": "ANM_CHEN_GLUCOSE_IDLE_03.png",
    "width": 1672,
    "height": 941,
    "mode": "RGBA",
    "category": "ANM"
  },
  {
    "file": "ANM_CHEN_HAND_KNIT_RUB_01.png",
    "width": 1672,
    "height": 941,
    "mode": "RGBA",
    "category": "ANM"
  },
  {
    "file": "ANM_CHEN_HAND_KNIT_RUB_02.png",
    "width": 1672,
    "height": 941,
    "mode": "RGBA",
    "category": "ANM"
  },
  {
    "file": "ANM_CHEN_HAND_KNIT_RUB_03.png",
    "width": 1672,
    "height": 941,
    "mode": "RGBA",
    "category": "ANM"
  },
  {
    "file": "ANM_CHEN_PHONE_DIM_01.png",
    "width": 1672,
    "height": 941,
    "mode": "RGBA",
    "category": "ANM"
  },
  {
    "file": "ANM_CHEN_PHONE_DIM_02.png",
    "width": 1672,
    "height": 941,
    "mode": "RGBA",
    "category": "ANM"
  },
  {
    "file": "ANM_CHEN_PHONE_DIM_03.png",
    "width": 1672,
    "height": 941,
    "mode": "RGBA",
    "category": "ANM"
  },
  {
    "file": "ANM_LI_CANE_GLANCE_01.png",
    "width": 1672,
    "height": 941,
    "mode": "RGBA",
    "category": "ANM"
  },
  {
    "file": "ANM_LI_CANE_GLANCE_02.png",
    "width": 1672,
    "height": 941,
    "mode": "RGBA",
    "category": "ANM"
  },
  {
    "file": "ANM_LI_FOOTSTEP_01.png",
    "width": 1672,
    "height": 941,
    "mode": "RGBA",
    "category": "ANM"
  },
  {
    "file": "ANM_LI_FOOTSTEP_02.png",
    "width": 1672,
    "height": 941,
    "mode": "RGBA",
    "category": "ANM"
  },
  {
    "file": "ANM_LI_FOOTSTEP_03.png",
    "width": 1672,
    "height": 941,
    "mode": "RGBA",
    "category": "ANM"
  },
  {
    "file": "ANM_LI_HAND_REACH_01.png",
    "width": 1672,
    "height": 941,
    "mode": "RGBA",
    "category": "ANM"
  },
  {
    "file": "ANM_LI_HAND_REACH_02.png",
    "width": 1672,
    "height": 941,
    "mode": "RGBA",
    "category": "ANM"
  },
  {
    "file": "ANM_LI_HAND_REACH_03.png",
    "width": 1672,
    "height": 941,
    "mode": "RGBA",
    "category": "ANM"
  },
  {
    "file": "ANM_LI_WINDOW_GLANCE_01.png",
    "width": 1672,
    "height": 941,
    "mode": "RGBA",
    "category": "ANM"
  },
  {
    "file": "ANM_LI_WINDOW_GLANCE_02.png",
    "width": 1672,
    "height": 941,
    "mode": "RGBA",
    "category": "ANM"
  },
  {
    "file": "ANM_LI_WINDOW_GLANCE_03.png",
    "width": 1672,
    "height": 941,
    "mode": "RGBA",
    "category": "ANM"
  },
  {
    "file": "ANM_WANG_HAND_WITHDRAW_01.png",
    "width": 1672,
    "height": 941,
    "mode": "RGBA",
    "category": "ANM"
  },
  {
    "file": "ANM_WANG_HAND_WITHDRAW_02.png",
    "width": 1672,
    "height": 941,
    "mode": "RGBA",
    "category": "ANM"
  },
  {
    "file": "ANM_WANG_HAND_WITHDRAW_03.png",
    "width": 1672,
    "height": 941,
    "mode": "RGBA",
    "category": "ANM"
  },
  {
    "file": "ANM_WANG_MEDICINE_TURN_01.png",
    "width": 1672,
    "height": 941,
    "mode": "RGBA",
    "category": "ANM"
  },
  {
    "file": "ANM_WANG_MEDICINE_TURN_02.png",
    "width": 1672,
    "height": 941,
    "mode": "RGBA",
    "category": "ANM"
  },
  {
    "file": "ANM_WANG_MEDICINE_TURN_03.png",
    "width": 1672,
    "height": 941,
    "mode": "RGBA",
    "category": "ANM"
  },
  {
    "file": "ANM_WANG_UTENSIL_SLIP_01.png",
    "width": 1672,
    "height": 941,
    "mode": "RGBA",
    "category": "ANM"
  },
  {
    "file": "ANM_WANG_UTENSIL_SLIP_02.png",
    "width": 1672,
    "height": 941,
    "mode": "RGBA",
    "category": "ANM"
  },
  {
    "file": "ANM_WANG_UTENSIL_SLIP_03.png",
    "width": 1672,
    "height": 941,
    "mode": "RGBA",
    "category": "ANM"
  },
  {
    "file": "CLUE_CHEN_CALENDAR.png",
    "width": 960,
    "height": 540,
    "mode": "RGBA",
    "category": "CLUE"
  },
  {
    "file": "CLUE_CHEN_FAMILY_PHOTO.png",
    "width": 960,
    "height": 540,
    "mode": "RGBA",
    "category": "CLUE"
  },
  {
    "file": "CLUE_CHEN_KNITTING.png",
    "width": 960,
    "height": 540,
    "mode": "RGBA",
    "category": "CLUE"
  },
  {
    "file": "CLUE_CHEN_PILL_BOX.png",
    "width": 960,
    "height": 540,
    "mode": "RGBA",
    "category": "CLUE"
  },
  {
    "file": "CLUE_CHEN_RECORD_BOOK.png",
    "width": 960,
    "height": 540,
    "mode": "RGBA",
    "category": "CLUE"
  },
  {
    "file": "CLUE_CHEN_TEST_STRIPS.png",
    "width": 960,
    "height": 540,
    "mode": "RGBA",
    "category": "CLUE"
  },
  {
    "file": "CLUE_LI_BIRTHDAY_CALENDAR.png",
    "width": 960,
    "height": 540,
    "mode": "RGBA",
    "category": "CLUE"
  },
  {
    "file": "CLUE_LI_CALL_BELL.png",
    "width": 960,
    "height": 540,
    "mode": "RGBA",
    "category": "CLUE"
  },
  {
    "file": "CLUE_LI_HANDRAIL_WEAR.png",
    "width": 960,
    "height": 540,
    "mode": "RGBA",
    "category": "CLUE"
  },
  {
    "file": "CLUE_LI_ROOM_PHOTO.png",
    "width": 960,
    "height": 540,
    "mode": "RGBA",
    "category": "CLUE"
  },
  {
    "file": "CLUE_LI_WORN_SHOES.png",
    "width": 960,
    "height": 540,
    "mode": "RGBA",
    "category": "CLUE"
  },
  {
    "file": "CLUE_WANG_CLOCK.png",
    "width": 960,
    "height": 540,
    "mode": "RGBA",
    "category": "CLUE"
  },
  {
    "file": "CLUE_WANG_FAMILY_PHOTO.png",
    "width": 960,
    "height": 540,
    "mode": "RGBA",
    "category": "CLUE"
  },
  {
    "file": "CLUE_WANG_MEAL_UNTOUCHED.png",
    "width": 960,
    "height": 540,
    "mode": "RGBA",
    "category": "CLUE"
  },
  {
    "file": "CLUE_WANG_WATER_MEDICINE.png",
    "width": 960,
    "height": 540,
    "mode": "RGBA",
    "category": "CLUE"
  },
  {
    "file": "FX_ACTION_AVAILABLE.png",
    "width": 1672,
    "height": 941,
    "mode": "RGBA",
    "category": "FX"
  },
  {
    "file": "FX_ACTION_CONFIRM.png",
    "width": 1672,
    "height": 941,
    "mode": "RGBA",
    "category": "FX"
  },
  {
    "file": "FX_ACTION_HOVER.png",
    "width": 1672,
    "height": 941,
    "mode": "RGBA",
    "category": "FX"
  },
  {
    "file": "FX_CLUE_FOCUS_GLOW.png",
    "width": 1672,
    "height": 941,
    "mode": "RGBA",
    "category": "FX"
  },
  {
    "file": "FX_CLUE_PEEKED_MARK.png",
    "width": 1672,
    "height": 941,
    "mode": "RGBA",
    "category": "FX"
  },
  {
    "file": "FX_CLUE_RECORDED_MARK.png",
    "width": 1672,
    "height": 941,
    "mode": "RGBA",
    "category": "FX"
  },
  {
    "file": "FX_HOTSPOT_PULSE.png",
    "width": 1672,
    "height": 941,
    "mode": "RGBA",
    "category": "FX"
  },
  {
    "file": "FX_SCENE_DIM_MASK.png",
    "width": 1672,
    "height": 941,
    "mode": "RGBA",
    "category": "FX"
  }
]